hybrid_index/__init__.py
hybrid_index/index.py
hybrid_index-0.1.0.dist-info/METADATA
hybrid_index-0.1.0.dist-info/WHEEL
hybrid_index-0.1.0.dist-info/top_level.txt
hybrid_index-0.1.0.dist-info/RECORD
