Metadata-Version: 2.1
Name: hybrid-index
Version: 0.1.0
Summary: Easy to use hybrid index for semantic + keyword search
Home-page: https://github.com/gigagiova/hybrid-index
Author: Giovanni del Gallo
Author-email: Giovanni del Gallo <giovanni@livesey.ai>
Project-URL: Home, https://github.com/gigagiova/hybrid-index
Classifier: License :: OSI Approved :: MIT License
Classifier: Programming Language :: Python :: 3.10
Classifier: Operating System :: OS Independent
Requires-Python: >=3.10
Requires-Dist: aiohttp (>=3.8.4)
Requires-Dist: aiosignal (>=1.3.1)
Requires-Dist: async-timeout (>=4.0.2)
Requires-Dist: attrs (>=23.1.0)
Requires-Dist: certifi (>=2023.5.7)
Requires-Dist: charset-normalizer (>=3.1.0)
Requires-Dist: click
Requires-Dist: distlib (>=0.3.6)
Requires-Dist: faiss-gpu (>=1.7.2)
Requires-Dist: filelock (>=3.10.7)
Requires-Dist: frozenlist (>=1.3.3)
Requires-Dist: idna (>=3.4)
Requires-Dist: mkl-fft (>=1.3.6)
Requires-Dist: mkl-service (>=2.4.0)
Requires-Dist: multidict (>=6.0.4)
Requires-Dist: nltk
Requires-Dist: numpy
Requires-Dist: openai (>=0.27.7)
Requires-Dist: platformdirs (>=3.2.0)
Requires-Dist: regex
Requires-Dist: requests (>=2.31.0)
Requires-Dist: urllib3 (>=2.0.2)
Requires-Dist: virtualenv (>=20.21.0)
Requires-Dist: yarl (>=1.9.2)
Provides-Extra: dev
Requires-Dist: pytest (>=7.0) ; extra == 'dev'
Requires-Dist: twine (>=4.0.2) ; extra == 'dev'
